ctclean
setup.py
ctlookup/__init__.py
ctlookup/config.py
ctlookup/lookup.py
ctlookup/data/ctnamecleaner.csv
ctnamecleaner.egg-info/PKG-INFO
ctnamecleaner.egg-info/SOURCES.txt
ctnamecleaner.egg-info/dependency_links.txt
ctnamecleaner.egg-info/requires.txt
ctnamecleaner.egg-info/top_level.txt