Metadata-Version: 1.1
Name: ctnamecleaner
Version: 0.10.1
Summary: Replace village names and commonly-misspelled Connecticut town names with real town/city names.
Home-page: https://github.com/jakekara/ctnamecleaner-py
Author: Jake Kara
Author-email: jake@jakekara.com
License: GPL-3.0
Download-URL: https://pypi.python.org/pypi/ctnamecleaner/
Platform: UNKNOWN
